odoo/addons/purchase_stock_return_request/README.rst
odoo/addons/purchase_stock_return_request/__init__.py
odoo/addons/purchase_stock_return_request/__manifest__.py
odoo/addons/purchase_stock_return_request/i18n/es.po
odoo/addons/purchase_stock_return_request/i18n/purchase_stock_return_request.pot
odoo/addons/purchase_stock_return_request/models/__init__.py
odoo/addons/purchase_stock_return_request/models/stock_return_request.py
odoo/addons/purchase_stock_return_request/readme/CONTRIBUTORS.rst
odoo/addons/purchase_stock_return_request/readme/DESCRIPTION.rst
odoo/addons/purchase_stock_return_request/readme/USAGE.rst
odoo/addons/purchase_stock_return_request/report/stock_return_report.xml
odoo/addons/purchase_stock_return_request/static/description/icon.png
odoo/addons/purchase_stock_return_request/static/description/index.html
odoo/addons/purchase_stock_return_request/tests/__init__.py
odoo/addons/purchase_stock_return_request/tests/test_stock_return_request.py
odoo/addons/purchase_stock_return_request/views/purchase_return_request_views.xml
odoo11_addon_purchase_stock_return_request-11.0.1.0.0.99.dev4.dist-info/METADATA
odoo11_addon_purchase_stock_return_request-11.0.1.0.0.99.dev4.dist-info/WHEEL
odoo11_addon_purchase_stock_return_request-11.0.1.0.0.99.dev4.dist-info/top_level.txt
odoo11_addon_purchase_stock_return_request-11.0.1.0.0.99.dev4.dist-info/RECORD
